pact_im/__init__.py
pact_im/base.py
pact_im/client.py
pact_im/exceptions.py
pact_im/utils.py
pact_im/schema/__init__.py
pact_im/schema/attachments.py
pact_im/schema/base.py
pact_im/schema/channels.py
pact_im/schema/companies.py
pact_im/schema/conversations.py
pact_im/schema/enums.py
pact_im/schema/messages.py
pact_im/schema/service_messages.py
pact_im/services/__init__.py
pact_im/services/attachment.py
pact_im/services/base.py
pact_im/services/channels.py
pact_im/services/companies.py
pact_im/services/conversations.py
pact_im/services/jobs.py
pact_im/services/messages.py
pact_im/services/service_messages.py
tests/__init__.py
tests/mock.py
tests/test_attachment.py
tests/test_channels.py
tests/test_client.py
tests/test_companies.py
tests/test_conversations.py
tests/test_jobs.py
tests/test_messages.py
tests/test_service_messages.py
pact_im-0.2.dist-info/METADATA
pact_im-0.2.dist-info/WHEEL
pact_im-0.2.dist-info/top_level.txt
pact_im-0.2.dist-info/RECORD
