Metadata-Version: 2.1
Name: pact-im
Version: 0.2
Summary: PactIM Python API
Home-page: UNKNOWN
Author: Pact LLC
License: UNKNOWN
Keywords: library,pact
Platform: UNKNOWN
Classifier: Programming Language :: Python :: 3.7
Classifier: Programming Language :: Python :: 3.8
Classifier: Programming Language :: Python :: 3.9
Classifier: License :: OSI Approved :: MIT License
Classifier: Operating System :: OS Independent
Requires-Dist: requests
Requires-Dist: pydantic
